basic_rest_endpoint/__init__.py
basic_rest_endpoint/rest.py
basic_rest_endpoint-1.2.0.dist-info/LICENSE
basic_rest_endpoint-1.2.0.dist-info/METADATA
basic_rest_endpoint-1.2.0.dist-info/WHEEL
basic_rest_endpoint-1.2.0.dist-info/top_level.txt
basic_rest_endpoint-1.2.0.dist-info/RECORD
