Metadata-Version: 2.1
Name: basic-rest-endpoint
Version: 1.2.0
Summary: A package that facilitates standard rest API flows.
Home-page: https://github.com/swimlane/basic-rest-endpoint
Author: Swimlane
Author-email: info@swimlane.com
Project-URL: Bug Tracker, https://github.com/swimlane/basic-rest-endpoint/issues
Classifier: Programming Language :: Python :: 3
Classifier: License :: OSI Approved :: MIT License
Classifier: Operating System :: OS Independent
Requires-Python: >=3.6
License-File: LICENSE
Requires-Dist: requests <3,>=2
Requires-Dist: swimlane-connector-exceptions <2,>=1.0.1
Requires-Dist: pyflattener <2
Requires-Dist: polling <1,>=0.3
